encord_agents/__init__.py
encord_agents/exceptions.py
encord_agents/py.typed
encord_agents/aws/__init__.py
encord_agents/aws/dependencies.py
encord_agents/aws/wrappers.py
encord_agents/cli/__init__.py
encord_agents/cli/main.py
encord_agents/cli/print.py
encord_agents/cli/test.py
encord_agents/core/__init__.py
encord_agents/core/constants.py
encord_agents/core/data_model.py
encord_agents/core/exceptions.py
encord_agents/core/ontology.py
encord_agents/core/rich_columns.py
encord_agents/core/settings.py
encord_agents/core/types.py
encord_agents/core/utils.py
encord_agents/core/video.py
encord_agents/core/vision.py
encord_agents/core/dependencies/__init__.py
encord_agents/core/dependencies/models.py
encord_agents/core/dependencies/serverless.py
encord_agents/core/dependencies/shares.py
encord_agents/core/dependencies/utils.py
encord_agents/fastapi/__init__.py
encord_agents/fastapi/cors.py
encord_agents/fastapi/dependencies.py
encord_agents/fastapi/utils.py
encord_agents/gcp/__init__.py
encord_agents/gcp/dependencies.py
encord_agents/gcp/wrappers.py
encord_agents/tasks/__init__.py
encord_agents/tasks/dependencies.py
encord_agents/tasks/models.py
encord_agents/tasks/runner/__init__.py
encord_agents/tasks/runner/queue_runner.py
encord_agents/tasks/runner/runner_base.py
encord_agents/tasks/runner/sequential_runner.py
encord_agents/utils/__init__.py
encord_agents/utils/colab.py
encord_agents/utils/generic_utils.py
encord_agents-0.2.6.dist-info/METADATA
encord_agents-0.2.6.dist-info/WHEEL
encord_agents-0.2.6.dist-info/entry_points.txt
encord_agents-0.2.6.dist-info/licenses/LICENSE
encord_agents-0.2.6.dist-info/RECORD
