Metadata-Version: 2.4
Name: encord-agents
Version: 0.2.6
Summary: A framework for producing custom agents for the Encord ecosystem.
Project-URL: Homepage, https://encord.com
Project-URL: Repository, https://github.com/encord-team/encord-agents
Project-URL: Documentation, https://agents-docs.encord.com
Author-email: Cord Technologies Limited <hello@encord.com>
License-Expression: Apache-2.0
License-File: LICENSE
Keywords: agent,agents,automation,data,encord,label,learning,machine,model,quality,test
Classifier: Environment :: Console
Classifier: Environment :: Web Environment
Classifier: Intended Audience :: Developers
Classifier: Intended Audience :: Education
Classifier: Intended Audience :: Information Technology
Classifier: Intended Audience :: Science/Research
Classifier: Operating System :: OS Independent
Classifier: Programming Language :: Python
Classifier: Programming Language :: Python :: 3.10
Classifier: Programming Language :: Python :: 3.11
Classifier: Programming Language :: Python :: 3.12
Classifier: Topic :: Scientific/Engineering
Classifier: Topic :: Scientific/Engineering :: Artificial Intelligence
Classifier: Topic :: Scientific/Engineering :: Information Analysis
Classifier: Topic :: Software Development
Classifier: Topic :: Software Development :: Quality Assurance
Requires-Python: >=3.10
Requires-Dist: encord>=0.1.169
Requires-Dist: numpy>=1.26.4
Requires-Dist: pydantic-settings<3,>=2.5.2
Requires-Dist: pydantic<3.0.0,>2.1.0
Requires-Dist: requests<3,>=2.32.3
Requires-Dist: typer>=0.12.5
Requires-Dist: typing-extensions>=4.8.0
Provides-Extra: vision
Requires-Dist: opencv-python-headless>=4.1; extra == 'vision'
